{
  "publisher": "remotionlab",
  "runtime": "remotion",
  "slug": "social-tiktok",
  "displayName": "Social Tiktok",
  "displayNameZh": "TikTok 视频帖子卡",
  "summary": "Social Tiktok component for Remotion.",
  "summaryZh": "适用于 Remotion 的TikTok 视频帖子卡组件。",
  "categories": [
    "social"
  ],
  "tags": [
    "remotion",
    "social",
    "tiktok"
  ],
  "status": "published",
  "versions": [
    {
      "version": "1.0.0",
      "changelog": "Initial migrated release.",
      "preview": {
        "thumbnailUrl": "https://remotionhub.oss-cn-shenzhen.aliyuncs.com/showcase/social-tiktok/7fde308d905a-thumb.jpg",
        "previewVideoUrl": "https://remotionhub.oss-cn-shenzhen.aliyuncs.com/showcase/social-tiktok/a8a82b9cb092-preview.mp4",
        "demoUrl": "https://remotionlab.com/showcase/social-tiktok"
      },
      "metadata": {
        "runtime": "remotion",
        "entryPoint": "src/SocialTiktok.tsx",
        "aspectRatios": [
          "16:9"
        ],
        "durationFrames": 120,
        "fps": 30
      },
      "tags": [
        "social",
        "tiktok"
      ],
      "artifact": {
        "kind": "github-source",
        "githubSource": {
          "repo": "remotionhub/remotionhub-assets",
          "ref": "main",
          "commit": "8731f30e62a5973afc393494d5430648d5fbf7c7",
          "path": "remotion/social-tiktok"
        },
        "license": "MIT",
        "usageMarkdown": "Copy `remotion/social-tiktok/src/SocialTiktok.tsx` into your Remotion project, import `SocialTiktok` and `socialTiktokDefaultProps`, then register the composition.",
        "agentPrompt": "Add the Social Tiktok Remotion asset from remotionhub/remotionhub-assets at remotion/social-tiktok to my project. Preserve the exported SocialTiktokProps API and register the SocialTiktok composition with the default props."
      }
    }
  ]
}
